{
  "card_id": "math_12_Calculus2SchoolBook_p022_c01",
  "main_subject": "math",
  "subsubject": "function",
  "tag": "math/function",
  "summary": "تعریف توابع صعودی، نزولی، یکنوا و ثابت بر اساس تغییرات مقدار تابع در بازه‌های مشخص.",
  "key_points": [
    "تابع صعودی: در بازه‌ای که برای هر a < b داشته باشیم f(a) <= f(b).",
    "تابع نزولی: در بازه‌ای که برای هر a < b داشته باشیم f(a) >= f(b).",
    "تابع یکنوا: تابعی که در یک بازه فقط صعودی یا فقط نزولی باشد.",
    "تابع ثابت: تابعی که برای تمام مقادیر x در یک بازه، مقدار f(x) ثابت باشد؛ این تابع هم صعودی و هم نزولی محسوب می‌شود."
  ],
  "main_text": "اگر برای هر دو نقطه a و b از دامنه تابع f که a < b، داشته باشیم f(a) <= f(b)، آنگاه f را تابعی صعودی می‌نامیم. تابع f را در یک بازه، صعودی می‌گوییم، اگر برای هر دو مقدار a و b در این بازه که a < b، آنگاه f(a) <= f(b). در فاصله ای که یک تابع صعودی است، با حرکت روی نمودار (از چپ به راست)، روبه پایین نخواهیم رفت. تابع f را در یک بازه، نزولی می‌گوییم، اگر برای هر دو مقدار a و b در این بازه که a < b، آنگاه f(a) >= f(b). در فاصله ای که یک تابع نزولی است، با حرکت روی نمودار (از چپ به راست)، روبه بالا نخواهیم رفت. به تابعی که در یک بازه فقط صعودی یا فقط نزولی باشد، یکنوا می‌گوییم. تابع f را در یک بازه، ثابت می‌گوییم، اگر برای تمام مقادیر x در این بازه، مقدار f(x) ثابت باشد. با توجه به تعاریف بالا، تابع ثابت در یک بازه، هم صعودی و هم نزولی محسوب می‌شود.",
  "other_details": [
    "نمودارهای صعودی با حرکت از چپ به راست روبه بالا یا افقی هستند و هرگز روبه پایین نمی‌روند.",
    "نمودارهای نزولی با حرکت از چپ به راست روبه پایین یا افقی هستند و هرگز روبه بالا نمی‌روند."
  ],
  "source_page": 22,
  "image_path": "books/Calculus2SchoolBook/page_022.png",
  "confidence": 0.95
}