{
  "card_id": "biology_12_Biology3SchoolBook_p033_c01",
  "main_subject": "biology",
  "subsubject": "genetics",
  "tag": "biology/genetics",
  "summary": "رشته مورد رونویسی یک ژن ممکن است با رشته مجاور خود یکسان یا متفاوت باشد. همان‌طور که در شکل ۳ دیده می‌شود، رشته دنای مورد رونویسی برای سه ژن نشان داده شده یکسان نیست و فقط یکی از دو رشته هر ژن رونویسی می‌شود.",
  "key_points": [
    "رشته مورد رونویسی یک ژن ممکن است با رشته مجاور خود یکسان یا متفاوت باشد.",
    "فقط یکی از دو رشته هر ژن رونویسی می‌شود."
  ],
  "main_text": "رشته مورد رونویسی یک ژن ممکن است با رشته مورد رونویسی ژن مجاور خود یکسان یا متفاوت باشد. همان طور که در شکل ۳ می‌بینید رشته دنای مورد رونویسی برای سه ژن نشان داده شده یکسان نیست. شکل ۳- همان طور که در شکل مشاهده می‌شود، فقط یکی از دو رشته هر ژن رونویسی می‌شود.",
  "other_details": [
    "شکل ۳: رونویسی DNA برای سه ژن نشان داده شده است.",
    "ژن ۱",
    "ژن ۲",
    "ژن ۳",
    "راه انداز (Promoter)",
    "رنا بسپاراز (RNA polymerase)",
    "رنای در حال رونویسی (RNA being transcribed)"
  ],
  "source_page": 33,
  "image_path": "books/Biology3SchoolBook/page_033.png",
  "confidence": 0.95
}